LICENSE
MANIFEST.in
README.rst
setup.py
bin/errata-tool
errata_tool/__init__.py
errata_tool/bug.py
errata_tool/build.py
errata_tool/cdn_repo.py
errata_tool/connector.py
errata_tool/erratum.py
errata_tool/exception.py
errata_tool/jira_issue.py
errata_tool/product.py
errata_tool/product_version.py
errata_tool/products.py
errata_tool/release.py
errata_tool/security.py
errata_tool/user.py
errata_tool/variant.py
errata_tool.egg-info/PKG-INFO
errata_tool.egg-info/SOURCES.txt
errata_tool.egg-info/dependency_links.txt
errata_tool.egg-info/not-zip-safe
errata_tool.egg-info/requires.txt
errata_tool.egg-info/top_level.txt
errata_tool/cli/__init__.py
errata_tool/cli/advisory.py
errata_tool/cli/bug.py
errata_tool/cli/build.py
errata_tool/cli/dump-config.py
errata_tool/cli/jiraissue.py
errata_tool/cli/main.py
errata_tool/cli/product.py
errata_tool/cli/release.py
errata_tool/tests/__init__.py
errata_tool/tests/__init__.pyc
errata_tool/tests/conftest.py
errata_tool/tests/test_add_builds.py
errata_tool/tests/test_add_cc.py
errata_tool/tests/test_advisory.py
errata_tool/tests/test_bug.py
errata_tool/tests/test_build.py
errata_tool/tests/test_cdn_repos.py
errata_tool/tests/test_change_docs_reviewer.py
errata_tool/tests/test_comments.py
errata_tool/tests/test_external_tests.py
errata_tool/tests/test_init.py
errata_tool/tests/test_jiraissue.py
errata_tool/tests/test_metadata_cdn_repos.py
errata_tool/tests/test_product.py
errata_tool/tests/test_product_version.py
errata_tool/tests/test_product_versions.py
errata_tool/tests/test_products.py
errata_tool/tests/test_release.py
errata_tool/tests/test_reload_builds.py
errata_tool/tests/test_remove_builds.py
errata_tool/tests/test_rhsa_cve_list.py
errata_tool/tests/test_rhsa_synopsis.py
errata_tool/tests/test_text_only_repos.py
errata_tool/tests/test_variant.py
errata_tool/tests/test_variants.py
errata_tool/tests/__pycache__/__init__.cpython-311.pyc
errata_tool/tests/__pycache__/__init__.cpython-36.pyc
errata_tool/tests/__pycache__/__init__.cpython-39.pyc
errata_tool/tests/__pycache__/conftest.cpython-27-PYTEST.pyc
errata_tool/tests/__pycache__/conftest.cpython-311-pytest-7.2.2.pyc
errata_tool/tests/__pycache__/conftest.cpython-36-pytest-6.2.4.pyc
