Metadata-Version: 2.1
Name: errata-tool
Version: 1.32.0
Summary: Python API for Red Hat Errata Tool
Home-page: https://github.com/red-hat-storage/errata-tool
Author: Ken Dreyer
Author-email: kdreyer@redhat.com
License: MIT
Keywords: packaging,build
License-File: LICENSE
